pterrafile/__init__.py
pterrafile/__main__.py
pterrafile/constants.py
pterrafile/patch.py
pterrafile/repository.py
pterrafile-0.5.0.data/scripts/pterrafile
pterrafile-0.5.0.dist-info/LICENSE
pterrafile-0.5.0.dist-info/METADATA
pterrafile-0.5.0.dist-info/WHEEL
pterrafile-0.5.0.dist-info/top_level.txt
pterrafile-0.5.0.dist-info/RECORD
