Metadata-Version: 2.1
Name: pterrafile
Version: 0.5.0
Summary: Manage external Terraform modules.
Home-page: https://github.com/terraform-great-modules/python-terrafile
Author: Riccardo Scartozzi - Raymond Butcher
Author-email: UNKNOWN
License: MIT License
Platform: UNKNOWN
Requires-Dist: pyyaml
Requires-Dist: requests
